odoo/addons/account_move_update_analytic/README.rst
odoo/addons/account_move_update_analytic/__init__.py
odoo/addons/account_move_update_analytic/__manifest__.py
odoo/addons/account_move_update_analytic/i18n/account_move_update_analytic.pot
odoo/addons/account_move_update_analytic/i18n/es.po
odoo/addons/account_move_update_analytic/i18n/fr.po
odoo/addons/account_move_update_analytic/i18n/hr.po
odoo/addons/account_move_update_analytic/i18n/it.po
odoo/addons/account_move_update_analytic/i18n/pt_BR.po
odoo/addons/account_move_update_analytic/models/__init__.py
odoo/addons/account_move_update_analytic/models/account_move.py
odoo/addons/account_move_update_analytic/readme/CONTRIBUTORS.md
odoo/addons/account_move_update_analytic/readme/DESCRIPTION.md
odoo/addons/account_move_update_analytic/readme/USAGE.md
odoo/addons/account_move_update_analytic/security/ir.model.access.csv
odoo/addons/account_move_update_analytic/static/description/icon.png
odoo/addons/account_move_update_analytic/static/description/index.html
odoo/addons/account_move_update_analytic/static/description/update_from_invoice.png
odoo/addons/account_move_update_analytic/static/description/update_from_journals.png
odoo/addons/account_move_update_analytic/views/account_move_line_view.xml
odoo/addons/account_move_update_analytic/views/account_move_view.xml
odoo/addons/account_move_update_analytic/wizards/__init__.py
odoo/addons/account_move_update_analytic/wizards/account_move_update_analytic.py
odoo/addons/account_move_update_analytic/wizards/account_move_update_analytic_view.xml
odoo_addon_account_move_update_analytic-18.0.1.0.0.2.dist-info/METADATA
odoo_addon_account_move_update_analytic-18.0.1.0.0.2.dist-info/WHEEL
odoo_addon_account_move_update_analytic-18.0.1.0.0.2.dist-info/top_level.txt
odoo_addon_account_move_update_analytic-18.0.1.0.0.2.dist-info/RECORD
