Metadata-Version: 2.1
Name: odoo-addon-account_move_update_analytic
Version: 18.0.1.0.0.2
Requires-Python: >=3.10
Requires-Dist: odoo==18.0.*
Summary: This module allows the user to update analytic on posted moves
Home-page: https://github.com/OCA/account-analytic
License: AGPL-3
Author: Le Filament, Moduon, Odoo Community Association (OCA)
Author-email: support@odoo-community.org
Classifier: Programming Language :: Python
Classifier: Framework :: Odoo
Classifier: Framework :: Odoo :: 18.0
Classifier: License :: OSI Approved :: GNU Affero General Public License v3
